{
  "borg": "pl080c",
  "bankCount": 41,
  "banks": [
    {
      "file": "anim_g00_s00_idle.json",
      "group": 0,
      "slot": 0,
      "label": "idle",
      "frames": 140,
      "animJoints": 20,
      "rootSpanX": 0,
      "rootSpanY": 0,
      "rootSpanZ": 0
    },
    {
      "file": "anim_g00_s01_move.json",
      "group": 0,
      "slot": 1,
      "label": "move",
      "frames": 33,
      "animJoints": 19,
      "rootSpanX": 0,
      "rootSpanY": 0,
      "rootSpanZ": 0
    },
    {
      "file": "anim_g00_s02_dash_fwd.json",
      "group": 0,
      "slot": 2,
      "label": "dash_fwd",
      "frames": 41,
      "animJoints": 20,
      "rootSpanX": 0,
      "rootSpanY": 0,
      "rootSpanZ": 0
    },
    {
      "file": "anim_g00_s03_dash_back.json",
      "group": 0,
      "slot": 3,
      "label": "dash_back",
      "frames": 41,
      "animJoints": 20,
      "rootSpanX": 0,
      "rootSpanY": 0,
      "rootSpanZ": 450
    },
    {
      "file": "anim_g00_s04_dash_left.json",
      "group": 0,
      "slot": 4,
      "label": "dash_left",
      "frames": 41,
      "animJoints": 20,
      "rootSpanX": 500,
      "rootSpanY": 0,
      "rootSpanZ": 0
    },
    {
      "file": "anim_g00_s05_dash_right.json",
      "group": 0,
      "slot": 5,
      "label": "dash_right",
      "frames": 41,
      "animJoints": 20,
      "rootSpanX": 500,
      "rootSpanY": 0,
      "rootSpanZ": 0
    },
    {
      "file": "anim_g00_s06_jump_takeoff.json",
      "group": 0,
      "slot": 6,
      "label": "jump_takeoff",
      "frames": 89,
      "animJoints": 20,
      "rootSpanX": 0,
      "rootSpanY": 0,
      "rootSpanZ": 0
    },
    {
      "file": "anim_g00_s07_jump_land.json",
      "group": 0,
      "slot": 7,
      "label": "jump_land",
      "frames": 12,
      "animJoints": 20,
      "rootSpanX": 0,
      "rootSpanY": 0,
      "rootSpanZ": 0
    },
    {
      "file": "anim_g00_s08_turn.json",
      "group": 0,
      "slot": 8,
      "label": "turn",
      "frames": 38,
      "animJoints": 20,
      "rootSpanX": 0,
      "rootSpanY": 0,
      "rootSpanZ": 0
    },
    {
      "file": "anim_g00_s09_fly_transition.json",
      "group": 0,
      "slot": 9,
      "label": "fly_transition",
      "frames": 20,
      "animJoints": 20,
      "rootSpanX": 0,
      "rootSpanY": 0,
      "rootSpanZ": 0
    },
    {
      "file": "anim_g00_s14_pose_short.json",
      "group": 0,
      "slot": 14,
      "label": "pose_short",
      "frames": 2,
      "animJoints": 20,
      "rootSpanX": 0,
      "rootSpanY": 0,
      "rootSpanZ": 0
    },
    {
      "file": "anim_g00_s15_move_s15.json",
      "group": 0,
      "slot": 15,
      "label": "move_s15",
      "frames": 2,
      "animJoints": 20,
      "rootSpanX": 0,
      "rootSpanY": 0,
      "rootSpanZ": 0
    },
    {
      "file": "anim_g00_s23_boost.json",
      "group": 0,
      "slot": 23,
      "label": "boost",
      "frames": 61,
      "animJoints": 20,
      "rootSpanX": 0,
      "rootSpanY": 0,
      "rootSpanZ": 0
    },
    {
      "file": "anim_g00_s24_pose_short.json",
      "group": 0,
      "slot": 24,
      "label": "pose_short",
      "frames": 2,
      "animJoints": 20,
      "rootSpanX": 0,
      "rootSpanY": 0,
      "rootSpanZ": 0
    },
    {
      "file": "anim_g01_s00_attack_s0.json",
      "group": 1,
      "slot": 0,
      "label": "attack_s0",
      "frames": 2,
      "animJoints": 20,
      "rootSpanX": 0,
      "rootSpanY": 0,
      "rootSpanZ": 0
    },
    {
      "file": "anim_g01_s01_attack_lunge_s1.json",
      "group": 1,
      "slot": 1,
      "label": "attack_lunge_s1",
      "frames": 51,
      "animJoints": 20,
      "rootSpanX": 0,
      "rootSpanY": 0,
      "rootSpanZ": 126.5
    },
    {
      "file": "anim_g01_s02_attack_s2.json",
      "group": 1,
      "slot": 2,
      "label": "attack_s2",
      "frames": 31,
      "animJoints": 20,
      "rootSpanX": 0,
      "rootSpanY": 0,
      "rootSpanZ": 0
    },
    {
      "file": "anim_g01_s03_attack_s3.json",
      "group": 1,
      "slot": 3,
      "label": "attack_s3",
      "frames": 61,
      "animJoints": 20,
      "rootSpanX": 0,
      "rootSpanY": 0,
      "rootSpanZ": 0
    },
    {
      "file": "anim_g01_s04_attack_s4.json",
      "group": 1,
      "slot": 4,
      "label": "attack_s4",
      "frames": 61,
      "animJoints": 20,
      "rootSpanX": 0,
      "rootSpanY": 0,
      "rootSpanZ": 0
    },
    {
      "file": "anim_g01_s05_attack_lunge_s5.json",
      "group": 1,
      "slot": 5,
      "label": "attack_lunge_s5",
      "frames": 49,
      "animJoints": 20,
      "rootSpanX": 0,
      "rootSpanY": 0,
      "rootSpanZ": 34.119
    },
    {
      "file": "anim_g01_s06_attack_s6.json",
      "group": 1,
      "slot": 6,
      "label": "attack_s6",
      "frames": 41,
      "animJoints": 20,
      "rootSpanX": 0,
      "rootSpanY": 0,
      "rootSpanZ": 0
    },
    {
      "file": "anim_g01_s07_attack_s7.json",
      "group": 1,
      "slot": 7,
      "label": "attack_s7",
      "frames": 27,
      "animJoints": 20,
      "rootSpanX": 0,
      "rootSpanY": 0,
      "rootSpanZ": 0
    },
    {
      "file": "anim_g01_s08_attack_s8.json",
      "group": 1,
      "slot": 8,
      "label": "attack_s8",
      "frames": 18,
      "animJoints": 20,
      "rootSpanX": 0,
      "rootSpanY": 0,
      "rootSpanZ": 0
    },
    {
      "file": "anim_g01_s10_attack_s10.json",
      "group": 1,
      "slot": 10,
      "label": "attack_s10",
      "frames": 41,
      "animJoints": 20,
      "rootSpanX": 0,
      "rootSpanY": 0,
      "rootSpanZ": 0
    },
    {
      "file": "anim_g01_s11_attack_s11.json",
      "group": 1,
      "slot": 11,
      "label": "attack_s11",
      "frames": 51,
      "animJoints": 20,
      "rootSpanX": 0,
      "rootSpanY": 0,
      "rootSpanZ": 0
    },
    {
      "file": "anim_g01_s13_attack_s13.json",
      "group": 1,
      "slot": 13,
      "label": "attack_s13",
      "frames": 36,
      "animJoints": 20,
      "rootSpanX": 0,
      "rootSpanY": 0,
      "rootSpanZ": 0
    },
    {
      "file": "anim_g01_s14_attack_s14.json",
      "group": 1,
      "slot": 14,
      "label": "attack_s14",
      "frames": 16,
      "animJoints": 20,
      "rootSpanX": 0,
      "rootSpanY": 0,
      "rootSpanZ": 0
    },
    {
      "file": "anim_g01_s15_attack_s15.json",
      "group": 1,
      "slot": 15,
      "label": "attack_s15",
      "frames": 25,
      "animJoints": 20,
      "rootSpanX": 0,
      "rootSpanY": 0,
      "rootSpanZ": 0
    },
    {
      "file": "anim_g01_s16_attack_s16.json",
      "group": 1,
      "slot": 16,
      "label": "attack_s16",
      "frames": 11,
      "animJoints": 20,
      "rootSpanX": 0,
      "rootSpanY": 0,
      "rootSpanZ": 0
    },
    {
      "file": "anim_g01_s17_attack_s17.json",
      "group": 1,
      "slot": 17,
      "label": "attack_s17",
      "frames": 16,
      "animJoints": 20,
      "rootSpanX": 0,
      "rootSpanY": 0,
      "rootSpanZ": 0
    },
    {
      "file": "anim_g01_s18_attack_s18.json",
      "group": 1,
      "slot": 18,
      "label": "attack_s18",
      "frames": 42,
      "animJoints": 20,
      "rootSpanX": 0,
      "rootSpanY": 0,
      "rootSpanZ": 0
    },
    {
      "file": "anim_g01_s19_attack_s19.json",
      "group": 1,
      "slot": 19,
      "label": "attack_s19",
      "frames": 42,
      "animJoints": 20,
      "rootSpanX": 0,
      "rootSpanY": 0,
      "rootSpanZ": 0
    },
    {
      "file": "anim_g01_s20_attack_s20.json",
      "group": 1,
      "slot": 20,
      "label": "attack_s20",
      "frames": 42,
      "animJoints": 20,
      "rootSpanX": 0,
      "rootSpanY": 0,
      "rootSpanZ": 0
    },
    {
      "file": "anim_g01_s22_attack_s22.json",
      "group": 1,
      "slot": 22,
      "label": "attack_s22",
      "frames": 65,
      "animJoints": 20,
      "rootSpanX": 0,
      "rootSpanY": 0,
      "rootSpanZ": 0
    },
    {
      "file": "anim_g01_s23_attack_s23.json",
      "group": 1,
      "slot": 23,
      "label": "attack_s23",
      "frames": 10,
      "animJoints": 20,
      "rootSpanX": 0,
      "rootSpanY": 0,
      "rootSpanZ": 0
    },
    {
      "file": "anim_g03_s11_guard_s11.json",
      "group": 3,
      "slot": 11,
      "label": "guard_s11",
      "frames": 41,
      "animJoints": 20,
      "rootSpanX": 0,
      "rootSpanY": 0,
      "rootSpanZ": 0
    },
    {
      "file": "anim_g03_s12_guard_s12.json",
      "group": 3,
      "slot": 12,
      "label": "guard_s12",
      "frames": 49,
      "animJoints": 20,
      "rootSpanX": 0,
      "rootSpanY": 0,
      "rootSpanZ": 0
    },
    {
      "file": "anim_g03_s33_hit_react_s33.json",
      "group": 3,
      "slot": 33,
      "label": "hit_react_s33",
      "frames": 11,
      "animJoints": 13,
      "rootSpanX": 0,
      "rootSpanY": 0,
      "rootSpanZ": 0
    },
    {
      "file": "anim_g04_s00_special_s0.json",
      "group": 4,
      "slot": 0,
      "label": "special_s0",
      "frames": 81,
      "animJoints": 20,
      "rootSpanX": 0,
      "rootSpanY": 0,
      "rootSpanZ": 0
    },
    {
      "file": "anim_g04_s01_special_s1.json",
      "group": 4,
      "slot": 1,
      "label": "special_s1",
      "frames": 71,
      "animJoints": 20,
      "rootSpanX": 0,
      "rootSpanY": 0,
      "rootSpanZ": 0
    },
    {
      "file": "anim_g05_s01_death.json",
      "group": 5,
      "slot": 1,
      "label": "death",
      "frames": 181,
      "animJoints": 22,
      "rootSpanX": 0,
      "rootSpanY": 0,
      "rootSpanZ": 0
    }
  ]
}